intdash/__init__.py
intdash/_api_endpoints.py
intdash/_binaly_utils.py
intdash/_captures.py
intdash/_client.py
intdash/_data_points.py
intdash/_edges.py
intdash/_filter.py
intdash/_internal.py
intdash/_iscp.py
intdash/_measurement_basetimes.py
intdash/_measurement_markers.py
intdash/_measurements.py
intdash/_models.py
intdash/_protocol.py
intdash/_signals.py
intdash/_units.py
intdash/_utils.py
intdash/_websocket.py
intdash/data.py
intdash/pb/__init__.py
intdash/pb/data_response_pb2.py
intdash/pb/store_request_pb2.py
intdash/timeutils/__init__.py
intdash-2.1.1.dist-info/LICENSE
intdash-2.1.1.dist-info/METADATA
intdash-2.1.1.dist-info/WHEEL
intdash-2.1.1.dist-info/top_level.txt
intdash-2.1.1.dist-info/RECORD
