Metadata-Version: 2.1
Name: intdash
Version: 2.1.1
Summary: intdash SDK for Python
Home-page: https://docs.intdash.jp/sdk/python/latest/en/
Author: aptpod,Inc
Author-email: sdk-support@aptpod.co.jp
License: Apache License 2.0
Keywords: intdash,intdash SDK
Platform: UNKNOWN
Requires-Python: >=3.5
Requires-Dist: numpy
Requires-Dist: pandas
Requires-Dist: requests
Requires-Dist: tornado
Requires-Dist: debtcollector
Requires-Dist: protobuf
